Workbook
Name Amount: Loan!$B$3
Name Rate: Loan!$B$4
Name Months: Loan!$B$5

Sheet Sales
A1: Onyx Café — Sales 2026
A2: Takings by product and month, in euros
A4: Month | B4: Coffee | C4: Tea | D4: Pastries | E4: Total | F4: Change
A5: =DATE(2026,1,1) -> 46023 | B5: 3120.5 | C5: 1240.2 | D5: 2050 | E5: =SUM(B5:D5) -> 6410.7
A6: =DATE(2026,2,1) -> 46054 | B6: 2980.25 | C6: 1310 | D6: 1920.4 | E6: =SUM(B6:D6) -> 6210.65 | F6: =E6/E5-1 -> -0.031205641
A7: =DATE(2026,3,1) -> 46082 | B7: 3410 | C7: 1150.5 | D7: 2180.7 | E7: =SUM(B7:D7) -> 6741.2 | F7: =E7/E6-1 -> 0.085425841
A8: =DATE(2026,4,1) -> 46113 | B8: 3562.75 | C8: 980.75 | D8: 2240 | E8: =SUM(B8:D8) -> 6783.5 | F8: =E8/E7-1 -> 0.0062748472
A9: =DATE(2026,5,1) -> 46143 | B9: 3890.4 | C9: 870 | D9: 2360.2 | E9: =SUM(B9:D9) -> 7120.6 | F9: =E9/E8-1 -> 0.049694111
A10: =DATE(2026,6,1) -> 46174 | B10: 4210 | C10: 760.3 | D10: 2410.9 | E10: =SUM(B10:D10) -> 7381.2 | F10: =E10/E9-1 -> 0.036598039
A11: =DATE(2026,7,1) -> 46204 | B11: 4480.6 | C11: 690.1 | D11: 2520.5 | E11: =SUM(B11:D11) -> 7691.2 | F11: =E11/E10-1 -> 0.041998591
A12: =DATE(2026,8,1) -> 46235 | B12: 3950.2 | C12: 720 | D12: 2130 | E12: =SUM(B12:D12) -> 6800.2 | F12: =E12/E11-1 -> -0.11584668
A13: =DATE(2026,9,1) -> 46266 | B13: 3720 | C13: 910.45 | D13: 2290.6 | E13: =SUM(B13:D13) -> 6921.05 | F13: =E13/E12-1 -> 0.017771536
A14: =DATE(2026,10,1) -> 46296 | B14: 3641.5 | C14: 1120 | D14: 2310 | E14: =SUM(B14:D14) -> 7071.5 | F14: =E14/E13-1 -> 0.021738031
A15: =DATE(2026,11,1) -> 46327 | B15: 3380.9 | C15: 1290.8 | D15: 2240.35 | E15: =SUM(B15:D15) -> 6912.05 | F15: =E15/E14-1 -> -0.022548257
A16: =DATE(2026,12,1) -> 46357 | B16: 4120.3 | C16: 1420.6 | D16: 2870.25 | E16: =SUM(B16:D16) -> 8411.15 | F16: =E16/E15-1 -> 0.21688211
A17: Total | B17: =SUM(B5:B16) -> 44467.4 | C17: =SUM(C5:C16) -> 12463.7 | D17: =SUM(D5:D16) -> 27523.9 | E17: =SUM(E5:E16) -> 84455 | F17: =E16/E5-1 -> 0.31204861
A18: Average | B18: =AVERAGE(B5:B16) -> 3705.6167 | C18: =AVERAGE(C5:C16) -> 1038.6417 | D18: =AVERAGE(D5:D16) -> 2293.6583 | E18: =AVERAGE(E5:E16) -> 7037.9167
A19: Best month | B19: =INDEX(A5:A16,MATCH(MAX(E5:E16),E5:E16,0)) -> 46357 | C19: =MAX(E5:E16) -> 8411.15

Sheet Summary
A1: Summary of the year
A3: Product | B3: Takings | C3: Share
A4: Coffee | B4: =Sales!B17 -> 44467.4 | C4: =B4/$B$7 -> 0.52652182
A5: Tea | B5: =Sales!C17 -> 12463.7 | C5: =B5/$B$7 -> 0.147578
A6: Pastries | B6: =Sales!D17 -> 27523.9 | C6: =B6/$B$7 -> 0.32590018
A7: Total | B7: =SUM(B4:B6) -> 84455 | C7: =SUM(C4:C6) -> 1
A9: Busiest month | B9: =INDEX(Sales!A5:A16,MATCH(MAX(Sales!E5:E16),Sales!E5:E16,0)) -> 46357
A10: Quietest month | B10: =INDEX(Sales!A5:A16,MATCH(MIN(Sales!E5:E16),Sales!E5:E16,0)) -> 46054
A11: Months over 7,500 € | B11: =COUNTIF(Sales!E5:E16,">7500") -> 2
A12: Summer's share | B12: =SUMPRODUCT((MONTH(Sales!A5:A16)>=6)*(MONTH(Sales!A5:A16)<=8)*Sales!E5:E16)/B7 -> 0.25898526
A13: Coffee, trend a month | B13: =SLOPE(Sales!B5:B16,MONTH(Sales!A5:A16)) -> 61.05035
A14: Tea: best / worst | B14: =TEXT(MAX(Sales!C5:C16),"#,##0")&" / "&TEXT(MIN(Sales!C5:C16),"#,##0") -> 1,421 / 690

Sheet Loan
A1: Espresso machine loan
A3: Amount | B3: 12000
A4: Yearly rate | B4: 0.045
A5: Months | B5: 36
A6: Monthly payment | B6: =PMT(Rate/12,Months,-Amount) -> 356.96309
A7: Total interest | B7: =B6*Months-Amount -> 850.67137
A9: Month | B9: Payment | C9: Interest | D9: Principal | E9: Balance
A10: 1 | B10: =$B$6 -> 356.96309 | C10: =IPMT(Rate/12,A10,Months,-Amount) -> 45 | D10: =PPMT(Rate/12,A10,Months,-Amount) -> 311.96309 | E10: =Amount-D10 -> 11688.037
A11: 2 | B11: =$B$6 -> 356.96309 | C11: =IPMT(Rate/12,A11,Months,-Amount) -> 43.830138 | D11: =PPMT(Rate/12,A11,Months,-Amount) -> 313.13296 | E11: =E10-D11 -> 11374.904
A12: 3 | B12: =$B$6 -> 356.96309 | C12: =IPMT(Rate/12,A12,Months,-Amount) -> 42.65589 | D12: =PPMT(Rate/12,A12,Months,-Amount) -> 314.3072 | E12: =E11-D12 -> 11060.597
A13: 4 | B13: =$B$6 -> 356.96309 | C13: =IPMT(Rate/12,A13,Months,-Amount) -> 41.477238 | D13: =PPMT(Rate/12,A13,Months,-Amount) -> 315.48586 | E13: =E12-D13 -> 10745.111
A14: 5 | B14: =$B$6 -> 356.96309 | C14: =IPMT(Rate/12,A14,Months,-Amount) -> 40.294166 | D14: =PPMT(Rate/12,A14,Months,-Amount) -> 316.66893 | E14: =E13-D14 -> 10428.442
A15: 6 | B15: =$B$6 -> 356.96309 | C15: =IPMT(Rate/12,A15,Months,-Amount) -> 39.106657 | D15: =PPMT(Rate/12,A15,Months,-Amount) -> 317.85644 | E15: =E14-D15 -> 10110.586
A16: 7 | B16: =$B$6 -> 356.96309 | C16: =IPMT(Rate/12,A16,Months,-Amount) -> 37.914696 | D16: =PPMT(Rate/12,A16,Months,-Amount) -> 319.0484 | E16: =E15-D16 -> 9791.5371
A17: 8 | B17: =$B$6 -> 356.96309 | C17: =IPMT(Rate/12,A17,Months,-Amount) -> 36.718264 | D17: =PPMT(Rate/12,A17,Months,-Amount) -> 320.24483 | E17: =E16-D17 -> 9471.2923
A18: 9 | B18: =$B$6 -> 356.96309 | C18: =IPMT(Rate/12,A18,Months,-Amount) -> 35.517346 | D18: =PPMT(Rate/12,A18,Months,-Amount) -> 321.44575 | E18: =E17-D18 -> 9149.8466
A19: 10 | B19: =$B$6 -> 356.96309 | C19: =IPMT(Rate/12,A19,Months,-Amount) -> 34.311925 | D19: =PPMT(Rate/12,A19,Months,-Amount) -> 322.65117 | E19: =E18-D19 -> 8827.1954
A20: 11 | B20: =$B$6 -> 356.96309 | C20: =IPMT(Rate/12,A20,Months,-Amount) -> 33.101983 | D20: =PPMT(Rate/12,A20,Months,-Amount) -> 323.86111 | E20: =E19-D20 -> 8503.3343
A21: 12 | B21: =$B$6 -> 356.96309 | C21: =IPMT(Rate/12,A21,Months,-Amount) -> 31.887504 | D21: =PPMT(Rate/12,A21,Months,-Amount) -> 325.07559 | E21: =E20-D21 -> 8178.2587
A22: 13 | B22: =$B$6 -> 356.96309 | C22: =IPMT(Rate/12,A22,Months,-Amount) -> 30.66847 | D22: =PPMT(Rate/12,A22,Months,-Amount) -> 326.29462 | E22: =E21-D22 -> 7851.9641
... A45: 36 | B45: =$B$6 -> 356.96309 | C45: =IPMT(Rate/12,A45,Months,-Amount) -> 1.3336106 | D45: =PPMT(Rate/12,A45,Months,-Amount) -> 355.62948 | E45: =E44-D45 -> -2.5158897e-10
